unix_accounts/__init__.py
unix_accounts/error.py
unix_accounts/group.py
unix_accounts/password.py
unix_accounts/user.py
unix_accounts/bin/__init__.py
unix_accounts/bin/auth_tokens.py
unix_accounts/bin/cli.py
unix_accounts/bin/default_paths.py
unix_accounts/bin/package_base.py
unix_accounts/bin/server.py
unix_accounts/commandline/__init__.py
unix_accounts/commandline/command.py
unix_accounts/commandline/command_group.py
unix_accounts/commandline/command_group_members.py
unix_accounts/commandline/command_password.py
unix_accounts/commandline/command_unix_account.py
unix_accounts/commandline/command_user.py
unix_accounts/format/__init__.py
unix_accounts/format/groups_asciitable.py
unix_accounts/format/groups_json.py
unix_accounts/format/password_json.py
unix_accounts/format/users_asciitable.py
unix_accounts/format/users_json.py
unix_accounts/http_request/__init__.py
unix_accounts/http_request/group.py
unix_accounts/http_request/group_test.py
unix_accounts/http_request/password.py
unix_accounts/http_request/password_test.py
unix_accounts/http_request/user.py
unix_accounts/http_request/user_test.py
unix_accounts/storage/__init__.py
unix_accounts/storage/group_member.py
unix_accounts/storage/groups.py
unix_accounts/storage/password.py
unix_accounts/storage/users.py
unix_accounts/storage_sqlite/__init__.py
unix_accounts/storage_sqlite/api.py
unix_accounts/storage_sqlite/db.py
unix_accounts/storage_sqlite/db_sqlite.py
unix_accounts/storage_sqlite/group_api.py
unix_accounts/storage_sqlite/group_api_test.py
unix_accounts/storage_sqlite/group_fmt.py
unix_accounts/storage_sqlite/group_member_api.py
unix_accounts/storage_sqlite/group_member_api_test.py
unix_accounts/storage_sqlite/group_membership.py
unix_accounts/storage_sqlite/group_membership_test.py
unix_accounts/storage_sqlite/group_schema.py
unix_accounts/storage_sqlite/group_schema_test.py
unix_accounts/storage_sqlite/password_api.py
unix_accounts/storage_sqlite/password_api_test.py
unix_accounts-1.0.0.dist-info/LICENSE.txt
unix_accounts-1.0.0.dist-info/METADATA
unix_accounts-1.0.0.dist-info/WHEEL
unix_accounts-1.0.0.dist-info/entry_points.txt
unix_accounts-1.0.0.dist-info/top_level.txt
unix_accounts-1.0.0.dist-info/RECORD
