Metadata-Version: 2.1
Name: unix-accounts
Version: 1.0.0
Summary: Minimal and user-friendly database for sharing unix accounts between computers
Home-page: https://github.com/1nfiniteloop/unix-accounts
Author: Lars Gunnarsson
License: UNKNOWN
Platform: UNKNOWN
Classifier: Development Status :: 5 - Production/Stable
Classifier: Intended Audience :: System Administrators
Classifier: Topic :: Security
Classifier: Topic :: System :: Systems Administration
Classifier: License :: OSI Approved :: MIT License
Classifier: Programming Language :: Python :: 3
Classifier: Programming Language :: Python :: 3.6
Classifier: Programming Language :: Python :: 3.7
Classifier: Programming Language :: Python :: 3.8
Classifier: Programming Language :: Python :: 3.9
Classifier: Programming Language :: Python :: 3 :: Only
Requires-Python: >=3.6
License-File: LICENSE.txt
Requires-Dist: SQLAlchemy (>=1.4)
Requires-Dist: terminaltables (>=3.1)
Requires-Dist: tornado (>=6.1)
